{
    "target": {
        "user169": [],
        "user425": [
            "The Lion King",
            "A Separation",
            "Memento"
        ],
        "user321": [
            "The Lion King",
            "A Separation",
            "Memento"
        ],
        "user329": [
            "The Lion King",
            "A Separation",
            "Memento"
        ],
        "user303": [
            "The Lion King",
            "A Separation",
            "Memento"
        ],
        "user410": [
            "The Lion King",
            "A Separation",
            "Memento"
        ],
        "user112": [
            "The Lion King",
            "A Separation",
            "Memento"
        ],
        "user283": [
            "The Lion King",
            "A Separation",
            "Memento"
        ],
        "user203": [
            "The Lion King",
            "A Separation",
            "Memento"
        ],
        "user375": [],
        "user368": [
            "The Lion King",
            "A Separation",
            "Memento"
        ],
        "user421": [
            "The Lion King",
            "A Separation",
            "Memento"
        ],
        "user288": [
            "The Lion King",
            "A Separation",
            "Memento"
        ],
        "user111": [
            "The Lion King",
            "A Separation",
            "Memento"
        ],
        "user454": [
            "The Lion King",
            "A Separation",
            "Memento"
        ],
        "user164": [
            "The Lion King",
            "A Separation",
            "Memento"
        ],
        "user317": [
            "The Lion King",
            "A Separation",
            "Memento"
        ],
        "user215": [
            "The Lion King",
            "A Separation",
            "Memento"
        ],
        "user58": [
            "The Lion King",
            "A Separation",
            "Memento"
        ],
        "user456": [
            "The Lion King",
            "A Separation",
            "Memento"
        ],
        "user482": [
            "The Lion King",
            "A Separation",
            "Memento"
        ],
        "user221": [
            "The Lion King",
            "A Separation",
            "Memento"
        ],
        "user158": [
            "The Lion King",
            "A Separation",
            "Memento"
        ],
        "user94": [
            "The Lion King",
            "A Separation",
            "Memento"
        ],
        "user491": [
            "The Lion King",
            "A Separation",
            "Memento"
        ],
        "user92": [
            "The Lion King",
            "A Separation",
            "Memento"
        ],
        "user140": [
            "The Lion King",
            "A Separation",
            "Memento"
        ],
        "user69": [
            "The Lion King",
            "A Separation",
            "Memento"
        ],
        "user495": [
            "The Lion King",
            "A Separation",
            "Memento"
        ],
        "user219": [
            "The Lion King",
            "A Separation",
            "Memento"
        ],
        "user420": [
            "The Lion King",
            "A Separation",
            "Memento"
        ],
        "user183": [
            "The Lion King",
            "A Separation",
            "Memento"
        ],
        "user144": [
            "The Lion King",
            "A Separation",
            "Memento"
        ],
        "user180": [],
        "user145": [
            "The Lion King",
            "A Separation",
            "Memento"
        ],
        "user15": [
            "The Lion King",
            "A Separation",
            "Memento"
        ],
        "user218": [
            "The Lion King",
            "A Separation",
            "Memento"
        ],
        "user433": [
            "The Lion King",
            "A Separation",
            "Memento"
        ],
        "user47": [
            "The Lion King",
            "A Separation",
            "Memento"
        ],
        "user71": [
            "The Lion King",
            "A Separation",
            "Memento"
        ],
        "user285": [
            "The Lion King",
            "A Separation",
            "Memento"
        ],
        "user262": [
            "The Lion King",
            "A Separation",
            "Memento"
        ],
        "user268": [
            "The Lion King",
            "A Separation",
            "Memento"
        ],
        "user407": [],
        "user426": [
            "The Lion King",
            "A Separation",
            "Memento"
        ],
        "user472": [
            "The Lion King",
            "A Separation",
            "Memento"
        ],
        "user457": [
            "The Lion King",
            "A Separation",
            "Memento"
        ],
        "user305": [
            "The Shawshank Redemption",
            "12 Angry Men",
            "The Godfather"
        ],
        "user341": [
            "The Shawshank Redemption",
            "12 Angry Men",
            "The Godfather"
        ],
        "user48": [
            "The Shawshank Redemption",
            "12 Angry Men",
            "The Godfather"
        ],
        "user68": [
            "12 Angry Men",
            "The Godfather",
            "The Godfather Part II"
        ],
        "user480": [
            "The Shawshank Redemption",
            "12 Angry Men",
            "The Godfather"
        ],
        "user486": [
            "The Shawshank Redemption",
            "12 Angry Men",
            "The Godfather"
        ],
        "user311": [
            "The Shawshank Redemption",
            "12 Angry Men",
            "The Godfather"
        ],
        "user32": [
            "The Shawshank Redemption",
            "12 Angry Men",
            "The Godfather"
        ],
        "user250": [
            "The Shawshank Redemption",
            "12 Angry Men",
            "The Godfather"
        ],
        "user91": [
            "12 Angry Men",
            "The Godfather",
            "The Godfather Part II"
        ],
        "user323": [
            "The Shawshank Redemption",
            "12 Angry Men",
            "The Godfather"
        ],
        "user120": [
            "12 Angry Men",
            "The Godfather",
            "The Godfather Part II"
        ],
        "user67": [
            "The Shawshank Redemption",
            "12 Angry Men",
            "The Godfather"
        ],
        "user306": [
            "The Shawshank Redemption",
            "12 Angry Men",
            "The Godfather"
        ],
        "user190": [
            "The Shawshank Redemption",
            "12 Angry Men",
            "The Godfather"
        ],
        "user435": [
            "The Shawshank Redemption",
            "12 Angry Men",
            "The Godfather"
        ],
        "user290": [
            "The Shawshank Redemption",
            "12 Angry Men",
            "The Godfather"
        ],
        "user143": [
            "The Shawshank Redemption",
            "12 Angry Men",
            "The Godfather"
        ],
        "user147": [
            "The Shawshank Redemption",
            "12 Angry Men",
            "The Godfather"
        ],
        "user294": [
            "The Shawshank Redemption",
            "12 Angry Men",
            "The Godfather"
        ],
        "user313": [
            "The Shawshank Redemption",
            "12 Angry Men",
            "The Godfather"
        ],
        "user312": [
            "The Shawshank Redemption",
            "12 Angry Men",
            "The Godfather"
        ],
        "user493": [
            "The Shawshank Redemption",
            "12 Angry Men",
            "The Godfather"
        ],
        "user66": [
            "The Shawshank Redemption",
            "12 Angry Men",
            "The Godfather"
        ],
        "user35": [
            "The Shawshank Redemption",
            "12 Angry Men",
            "The Godfather Part II"
        ],
        "user343": [
            "The Shawshank Redemption",
            "12 Angry Men",
            "The Godfather"
        ],
        "user174": [
            "The Shawshank Redemption",
            "12 Angry Men",
            "The Godfather"
        ],
        "user202": [
            "The Shawshank Redemption",
            "12 Angry Men",
            "The Godfather"
        ],
        "user307": [
            "The Shawshank Redemption",
            "12 Angry Men",
            "The Godfather"
        ],
        "user234": [
            "The Shawshank Redemption",
            "12 Angry Men",
            "The Godfather"
        ],
        "user443": [
            "The Shawshank Redemption",
            "12 Angry Men",
            "The Godfather"
        ],
        "user346": [
            "The Shawshank Redemption",
            "12 Angry Men",
            "The Godfather"
        ],
        "user129": [
            "The Shawshank Redemption",
            "12 Angry Men",
            "The Godfather"
        ],
        "user278": [
            "The Shawshank Redemption",
            "12 Angry Men",
            "The Godfather"
        ],
        "user5": [
            "The Shawshank Redemption",
            "12 Angry Men",
            "The Godfather"
        ],
        "user402": [
            "The Shawshank Redemption",
            "12 Angry Men",
            "The Godfather"
        ],
        "user362": [
            "The Shawshank Redemption",
            "12 Angry Men",
            "The Godfather"
        ],
        "user327": [
            "The Shawshank Redemption",
            "12 Angry Men",
            "The Godfather"
        ],
        "user431": [
            "The Shawshank Redemption",
            "12 Angry Men",
            "The Godfather"
        ],
        "user468": [
            "The Shawshank Redemption",
            "12 Angry Men",
            "The Godfather"
        ],
        "user214": [
            "The Shawshank Redemption",
            "12 Angry Men",
            "The Godfather"
        ],
        "user331": [
            "The Shawshank Redemption",
            "12 Angry Men",
            "The Godfather"
        ],
        "user330": [
            "The Shawshank Redemption",
            "12 Angry Men",
            "The Godfather"
        ],
        "user296": [
            "The Shawshank Redemption",
            "12 Angry Men",
            "The Godfather"
        ],
        "user417": [
            "The Shawshank Redemption",
            "12 Angry Men",
            "The Godfather"
        ],
        "user103": [
            "The Shawshank Redemption",
            "12 Angry Men",
            "The Godfather"
        ],
        "user7": [
            "The Lion King",
            "A Separation",
            "Memento"
        ],
        "user46": [
            "The Lion King",
            "A Separation",
            "Memento"
        ],
        "user115": [
            "The Lion King",
            "A Separation",
            "Memento"
        ],
        "user119": [
            "The Lion King",
            "A Separation",
            "Memento"
        ],
        "user138": [
            "The Lion King",
            "A Separation",
            "Memento"
        ],
        "user170": [
            "The Lion King",
            "A Separation",
            "Memento"
        ],
        "user161": [
            "The Lion King",
            "A Separation",
            "Memento"
        ],
        "user9": [
            "The Lion King",
            "A Separation",
            "Memento"
        ],
        "user155": [
            "The Lion King",
            "A Separation",
            "Memento"
        ],
        "user97": [
            "The Lion King",
            "A Separation",
            "Memento"
        ],
        "user163": [
            "The Lion King",
            "A Separation",
            "Memento"
        ],
        "user49": [
            "The Lion King",
            "A Separation",
            "Memento"
        ],
        "user191": [
            "The Lion King",
            "A Separation",
            "Memento"
        ],
        "user122": [
            "The Lion King",
            "A Separation",
            "Memento"
        ],
        "user187": [
            "The Lion King",
            "A Separation",
            "Memento"
        ],
        "user181": [
            "The Lion King",
            "A Separation",
            "Memento"
        ],
        "user162": [
            "The Lion King",
            "A Separation",
            "Memento"
        ],
        "user150": [
            "The Lion King",
            "A Separation",
            "Memento"
        ],
        "user56": [
            "The Lion King",
            "A Separation",
            "Memento"
        ],
        "user153": [
            "The Lion King",
            "A Separation",
            "Memento"
        ],
        "user42": [
            "The Lion King",
            "A Separation",
            "Memento"
        ],
        "user64": [
            "The Lion King",
            "A Separation",
            "Memento"
        ],
        "user194": [
            "The Lion King",
            "A Separation",
            "Memento"
        ],
        "user11": [
            "The Lion King",
            "A Separation",
            "Memento"
        ],
        "user2": [
            "The Lion King",
            "A Separation",
            "Memento"
        ],
        "user125": [
            "The Lion King",
            "A Separation",
            "Memento"
        ],
        "user156": [
            "The Lion King",
            "A Separation",
            "Memento"
        ],
        "user105": [
            "The Lion King",
            "A Separation",
            "Memento"
        ],
        "user95": [
            "The Lion King",
            "A Separation",
            "Memento"
        ],
        "user51": [
            "The Lion King",
            "A Separation",
            "Memento"
        ],
        "user1": [
            "The Lion King",
            "A Separation",
            "Memento"
        ],
        "user75": [
            "The Lion King",
            "A Separation",
            "Memento"
        ],
        "user199": [
            "The Lion King",
            "A Separation",
            "Memento"
        ],
        "user136": [
            "The Lion King",
            "A Separation",
            "Memento"
        ],
        "user113": [
            "The Lion King",
            "A Separation",
            "Memento"
        ],
        "user59": [
            "The Lion King",
            "A Separation",
            "Memento"
        ],
        "user127": [
            "The Lion King",
            "A Separation",
            "Memento"
        ],
        "user26": [
            "The Lion King",
            "A Separation",
            "Memento"
        ],
        "user31": [
            "The Lion King",
            "A Separation",
            "Memento"
        ],
        "user185": [
            "The Lion King",
            "A Separation",
            "Memento"
        ],
        "user139": [
            "The Lion King",
            "A Separation",
            "Memento"
        ],
        "user40": [
            "The Lion King",
            "A Separation",
            "Memento"
        ],
        "user189": [
            "The Lion King",
            "A Separation",
            "Memento"
        ],
        "user80": [
            "The Lion King",
            "A Separation",
            "Memento"
        ],
        "user29": [
            "The Lion King",
            "A Separation",
            "Memento"
        ],
        "user160": [
            "The Lion King",
            "A Separation",
            "Memento"
        ],
        "user55": [
            "The Lion King",
            "A Separation",
            "Memento"
        ],
        "user6": [
            "The Lion King",
            "A Separation",
            "Memento"
        ],
        "user85": [
            "The Lion King",
            "A Separation",
            "Memento"
        ],
        "user177": [
            "The Lion King",
            "A Separation",
            "Memento"
        ]
    }
}